LICENSE
MANIFEST.in
README.md
setup.py
boxeeremotelib/__init__.py
boxeeremotelib/discoverer.py
boxeeremotelib/remote_commands.py
boxeeremotelib/utils.py
boxeeremotelib.egg-info/PKG-INFO
boxeeremotelib.egg-info/SOURCES.txt
boxeeremotelib.egg-info/dependency_links.txt
boxeeremotelib.egg-info/entry_points.txt
boxeeremotelib.egg-info/top_level.txt
boxeeremotelib.egg-info/zip-safe