Metadata-Version: 1.1
Name: boxeeremotelib
Version: 0.1
Summary: an interface to the boxee remote api
Home-page: https://github.com/knorby/boxeeremotelib
Author: Karl Norby
Author-email: karl.norby@gmail.com
License: BSD
Keywords: boxee remote entertainment library
Platform: any
Classifier: Development Status :: 3 - Alpha
Classifier: Topic :: Utilities
Classifier: License :: OSI Approved :: BSD License
Classifier: Topic :: Multimedia :: Sound/Audio :: Players
